whyis_classifier/__init__.py
whyis_classifier/classifier_agent.py
whyis_classifier/test_whyis_classifier.py
whyis_classifier/testclassifier.py
whyis_classifier/user_classifiers.py
whyis_classifier/whyisclassifier.py
whyis_classifier-0.0.1.data/scripts/whyisclassifiertest
whyis_classifier-0.0.1.dist-info/LICENSE
whyis_classifier-0.0.1.dist-info/METADATA
whyis_classifier-0.0.1.dist-info/WHEEL
whyis_classifier-0.0.1.dist-info/top_level.txt
whyis_classifier-0.0.1.dist-info/RECORD
