Metadata-Version: 2.1
Name: whyis-classifier
Version: 0.0.1
Summary: Classifier interface for Whyis
Home-page: https://github.com/roryschadler/whyis_classifier
Author: Rory Schadler
Author-email: rory.h.schadler.21@dartmouth.edu
License: UNKNOWN
Platform: UNKNOWN
Classifier: Programming Language :: Python :: 3
Classifier: License :: OSI Approved :: MIT License
Classifier: Operating System :: OS Independent
Requires-Python: >=3.5.2
Requires-Dist: rdflib
